holoaverage/__init__.py
holoaverage/__main__.py
holoaverage/average.py
holoaverage/camera.py
holoaverage/defocus.py
holoaverage/dm3.py
holoaverage/fft.py
holoaverage/filter.py
holoaverage/grid.py
holoaverage/hdf5.py
holoaverage/json_utils.py
holoaverage/main.py
holoaverage/rawalign.py
holoaverage/reconstruction.py
holoaverage/series.py
holoaverage/version.py
holoaverage-1.1.10.dist-info/licenses/LICENSE.txt
holoaverage-1.1.10.dist-info/METADATA
holoaverage-1.1.10.dist-info/WHEEL
holoaverage-1.1.10.dist-info/entry_points.txt
holoaverage-1.1.10.dist-info/top_level.txt
holoaverage-1.1.10.dist-info/RECORD
